effects/__init__.py
effects/fireplace.py
effects/raining.py
effects/steady_color.py
neopyxel/__init__.py
neopyxel/effect.py
neopyxel/neopyxel.py
neopyxel/effects/__init__.py
neopyxel/effects/fireplace.py
neopyxel/effects/raining.py
neopyxel/effects/steady_color.py
neopyxel/transitions/__init__.py
neopyxel/transitions/expand.py
transitions/__init__.py
transitions/expand.py
neopyxel-1.1.0.dist-info/LICENSE
neopyxel-1.1.0.dist-info/METADATA
neopyxel-1.1.0.dist-info/WHEEL
neopyxel-1.1.0.dist-info/top_level.txt
neopyxel-1.1.0.dist-info/RECORD
