Metadata-Version: 2.1
Name: neopyxel
Version: 1.1.0
Summary: High-level interface to control neopixel     led stripes with an arduino as relay
Home-page: https://github.com/valves-ops/neopyxel
Author: Vinicius Alves
License: UNKNOWN
Project-URL: Bug Reports, https://github.com/valves-ops/neopyxel/issues
Project-URL: Source, https://github.com/valves-ops/neopyxel
Keywords: arduino,neopixel,led
Platform: UNKNOWN
Classifier: Development Status :: 5 - Production/Stable
Classifier: Intended Audience :: Developers
Classifier: License :: OSI Approved :: GNU General Public License v3 (GPLv3)
Classifier: Programming Language :: Python :: 3
Classifier: Programming Language :: Python :: 3.5
Classifier: Programming Language :: Python :: 3.6
Classifier: Programming Language :: Python :: 3.7
Classifier: Programming Language :: Python :: 3.8
Classifier: Programming Language :: Python :: 3 :: Only
Requires-Python: >=3.5, <4
Requires-Dist: pyserial
